pecan_swagger/__init__.py
pecan_swagger/decorators.py
pecan_swagger/g.py
pecan_swagger/utils.py
pecan_swagger-0.1.2.dist-info/DESCRIPTION.rst
pecan_swagger-0.1.2.dist-info/METADATA
pecan_swagger-0.1.2.dist-info/RECORD
pecan_swagger-0.1.2.dist-info/WHEEL
pecan_swagger-0.1.2.dist-info/metadata.json
pecan_swagger-0.1.2.dist-info/pbr.json
pecan_swagger-0.1.2.dist-info/top_level.txt
