Metadata-Version: 2.0
Name: pecan-swagger
Version: 0.1.2
Summary: A project to produce swagger from pecan
Home-page: https://github.com/elmiko/pecan-swagger
Author: Michael McCune
Author-email: msm@opbstudios.com
License: BSD
Keywords: pecan swagger development
Platform: UNKNOWN
Classifier: Development Status :: 3 - Alpha
Classifier: Intended Audience :: Developers
Classifier: License :: OSI Approved :: BSD License
Classifier: Programming Language :: Python :: 2.7
Classifier: Programming Language :: Python :: 3.4
